py_clos
