Metadata-Version: 1.1
Name: PyCLOS
Version: 0.2
Summary: CLOS-style generic functions with annotation based syntax
Home-page: https://github.com/adh/py-clos
Author: Ales Hakl
Author-email: ales@hakl.net
License: MIT
Keywords: clos generic
Platform: UNKNOWN
Classifier: Development Status :: 3 - Alpha
Classifier: Intended Audience :: Developers
Classifier: License :: OSI Approved :: MIT License
Classifier: Programming Language :: Python :: 3
Classifier: Programming Language :: Python :: 3.3
Classifier: Programming Language :: Python :: 3.4
Classifier: Programming Language :: Python :: 3.5
